{
  "cv": {
    "per_fold": [
      {
        "n": 443,
        "n_pos": 17,
        "pr_auc": 0.865719862955807,
        "roc_auc": 0.9675504004418669,
        "f1": 0.47619047619047616,
        "precision": 0.32608695652173914,
        "recall": 0.8823529411764706,
        "confusion_matrix": [
          [
            395,
            31
          ],
          [
            2,
            15
          ]
        ],
        "fold": 0
      },
      {
        "n": 443,
        "n_pos": 17,
        "pr_auc": 0.7239874690640622,
        "roc_auc": 0.9302678818006075,
        "f1": 0.6976744186046512,
        "precision": 0.5769230769230769,
        "recall": 0.8823529411764706,
        "confusion_matrix": [
          [
            415,
            11
          ],
          [
            2,
            15
          ]
        ],
        "fold": 1
      },
      {
        "n": 443,
        "n_pos": 17,
        "pr_auc": 0.8403963001097684,
        "roc_auc": 0.9501518917426126,
        "f1": 0.5882352941176471,
        "precision": 0.4411764705882353,
        "recall": 0.8823529411764706,
        "confusion_matrix": [
          [
            407,
            19
          ],
          [
            2,
            15
          ]
        ],
        "fold": 2
      },
      {
        "n": 443,
        "n_pos": 17,
        "pr_auc": 0.7414624755428166,
        "roc_auc": 0.8892571112952222,
        "f1": 0.5416666666666666,
        "precision": 0.41935483870967744,
        "recall": 0.7647058823529411,
        "confusion_matrix": [
          [
            408,
            18
          ],
          [
            4,
            13
          ]
        ],
        "fold": 3
      },
      {
        "n": 443,
        "n_pos": 18,
        "pr_auc": 0.5153178398205952,
        "roc_auc": 0.9445751633986927,
        "f1": 0.5098039215686274,
        "precision": 0.3939393939393939,
        "recall": 0.7222222222222222,
        "confusion_matrix": [
          [
            405,
            20
          ],
          [
            5,
            13
          ]
        ],
        "fold": 4
      }
    ],
    "cv_mean": {
      "pr_auc": {
        "mean": 0.7373767894986099,
        "std": 0.12376680325132099
      },
      "roc_auc": {
        "mean": 0.9363604897358003,
        "std": 0.026405841378460273
      },
      "f1": {
        "mean": 0.5627141554296137,
        "std": 0.07693430685427277
      },
      "precision": {
        "mean": 0.4314961473364246,
        "std": 0.08235498663270213
      },
      "recall": {
        "mean": 0.826797385620915,
        "std": 0.06935499814317547
      }
    }
  },
  "test": {
    "n": 554,
    "n_pos": 22,
    "pr_auc": 0.6665164246243859,
    "roc_auc": 0.9207963089542037,
    "f1": 0.6666666666666666,
    "precision": 0.6521739130434783,
    "recall": 0.6818181818181818,
    "confusion_matrix": [
      [
        524,
        8
      ],
      [
        7,
        15
      ]
    ]
  }
}